django_vastbase_backend/__init__.py
django_vastbase_backend/base.py
django_vastbase_backend/client.py
django_vastbase_backend/creation.py
django_vastbase_backend/features.py
django_vastbase_backend/introspection.py
django_vastbase_backend/operations.py
django_vastbase_backend/schema.py
django_vastbase_backend-0.1.2.dist-info/licenses/LICENSE
django_vastbase_backend-0.1.2.dist-info/METADATA
django_vastbase_backend-0.1.2.dist-info/WHEEL
django_vastbase_backend-0.1.2.dist-info/top_level.txt
django_vastbase_backend-0.1.2.dist-info/RECORD
