Metadata-Version: 2.4
Name: django_vastbase_backend
Version: 0.1.2
Summary: django backend for vastbase
Author-email: vastdata <wangxy3@vastdata.com.cn>
License: MIT
Project-URL: Homepage, https://github.com/vastdata/django_vastbase_backend
Requires-Python: >=3.8
License-File: LICENSE
Requires-Dist: django>=4.2
Requires-Dist: psycopg2-binary>=2.9.10
Dynamic: license-file
